mklcomp/__init__.py
mklcomp/mklcomp.py
luigi_completion-0.0.2.dist-info/LICENSE
luigi_completion-0.0.2.dist-info/METADATA
luigi_completion-0.0.2.dist-info/WHEEL
luigi_completion-0.0.2.dist-info/entry_points.txt
luigi_completion-0.0.2.dist-info/top_level.txt
luigi_completion-0.0.2.dist-info/RECORD
