Metadata-Version: 2.1
Name: luigi-completion
Version: 0.0.2
Summary: completion for luigi on bash, zsh
Home-page: https://github.com/vaaaaanquish/luigi_completion
Author: vaaaaanquish
Author-email: 6syun9@gmail.com
License: MIT
Platform: any
Classifier: Programming Language :: Python :: 3.6
